CHANGES.txt
MANIFEST.in
README.txt
setup.py
src/collective/__init__.py
src/collective.recipe.lasso.egg-info/PKG-INFO
src/collective.recipe.lasso.egg-info/SOURCES.txt
src/collective.recipe.lasso.egg-info/dependency_links.txt
src/collective.recipe.lasso.egg-info/entry_points.txt
src/collective.recipe.lasso.egg-info/not-zip-safe
src/collective.recipe.lasso.egg-info/requires.txt
src/collective.recipe.lasso.egg-info/top_level.txt
src/collective/recipe/__init__.py
src/collective/recipe/lasso/__init__.py