Metadata-Version: 1.0
Name: collective.recipe.lasso
Version: 0.1
Summary: Buildout recipe to install Lasso (SSO library)
Home-page: http://shane.willowrise.com
Author: Shane Hathaway
Author-email: shane@hathawaymix.org
License: ZPL
Keywords: buildout recipe lasso sso saml
Platform: UNKNOWN
Classifier: Development Status :: 3 - Alpha
Classifier: Intended Audience :: Developers
Classifier: Programming Language :: Python
Classifier: Topic :: Internet :: WWW/HTTP
